{"backend_api_menu_add.md":"e9062b77","backend_api_menu_delete.md":"34d7b519","backend_api_menu_index.md":"2bd80991","backend_api_menu_info.md":"bdc66939","backend_api_menu_power.md":"be0dc061","backend_api_menu_update.md":"f336addd","backend_api_passport_captcha.md":"2ab0a743","backend_api_passport_login.md":"bdb46f93","backend_api_passport_logout.md":"42353747","backend_api_role_add.md":"2a2dddfd","backend_api_role_index.md":"c2150dec","backend_index.md":"d6355e82","backend_laravel-lib_captcha.md":"d9b90bbf","backend_laravel-lib_date.md":"14712d7f","backend_laravel-lib_encrypt.md":"5dc07ab4","backend_laravel-lib_enum.md":"16c7c51c","backend_laravel-lib_identity.md":"d58c4dba","backend_laravel-lib_index.md":"762d957d","backend_laravel-lib_password.md":"30997305","backend_laravel-lib_repository.md":"bb8c2b85","frontend_components_iconsvg.md":"c555d454","frontend_components_ldform.md":"da92ce2d","frontend_components_ldhelp.md":"f0574644","frontend_components_ldtable.md":"82d3bb38","frontend_index.md":"d742a475","index.md":"8aa9d820"}
