{"backend_api_menu_add.md":"cd882c2d","backend_api_menu_delete.md":"1b7ab2b8","backend_api_menu_index.md":"b7af5182","backend_api_menu_info.md":"35fcbf0a","backend_api_menu_power.md":"dfaa8f4e","backend_api_menu_update.md":"be47170d","backend_api_passport_captcha.md":"d0ddf064","backend_api_passport_login.md":"94b1d80e","backend_api_passport_logout.md":"4549db81","backend_api_role_add.md":"14d8cea5","backend_api_role_index.md":"d5922a08","backend_index.md":"b45bde75","backend_laravel-lib_captcha.md":"574cb1de","backend_laravel-lib_date.md":"602afbef","backend_laravel-lib_encrypt.md":"8df455d4","backend_laravel-lib_enum.md":"e0b34cef","backend_laravel-lib_identity.md":"4da835bc","backend_laravel-lib_index.md":"0fa016b0","backend_laravel-lib_password.md":"cd677532","backend_laravel-lib_repository.md":"a07c517a","backend_laravel-lib_repository2.md":"a2c88262","frontend_components_iconsvg.md":"adf28b63","frontend_components_ldform.md":"02596d5c","frontend_components_ldhelp.md":"73606a9f","frontend_components_ldquill.md":"cad59def","frontend_components_ldtable.md":"f9b562d5","frontend_hooks_useboolean.md":"2f0e31dc","frontend_hooks_usemessage.md":"ec563a2f","frontend_hooks_usetoggle.md":"2e99ce69","frontend_index.md":"7d71b312","index.md":"641f358a"}
